{
  "users": [
    {
      "id": 1,
      "username": "kiran",
      "email": "kiran@gmail.com",
      "password": "kiran12",
      "confirmpass": "kiran12"
    },
    {
      "username": "abhi",
      "email": "abhi@gmail.com",
      "password": "abhi12",
      "id": 2
    },
    {
      "username": "shabaz",
      "email": "shabaz@gmail.com",
      "password": "shabaz12",
      "id": 3
    },
    {
      "username": "kiran",
      "email": "kiranmaigk445@gmail.com",
      "password": "kiran",
      "id": 4
    },
    {
      "username": "kiran",
      "email": "kiranmaigk445@gmail.com",
      "password": "kiran",
      "id": 5
    }
  ]
}